[{"title":"Ultralight Beam","artists":["Kanye West","The-Dream","Kelly Price","Kirk Franklin","Chance the Rapper"],"length":320.68,"ytid":["S_2C0ZX0M84"],"gid":"2413549"},{"title":"Father Stretch My Hands, Pt. 1","artists":["Kanye West","Kid Cudi"],"length":135.92,"ytid":["_MIsk8VoNhM"],"gid":"2412669"},{"title":"Pt. 2","artists":["Kanye West","Desiigner"],"length":130.293,"ytid":["V4XsK4ALZBI"],"gid":"2421998"},{"title":"Famous","artists":["Kanye West","Rihanna"],"length":196.04,"ytid":["Lq2TmRzg19k"],"gid":"2412662"},{"title":"Feedback","artists":["Kanye West"],"length":147.24,"ytid":["wcKkSyAip7c"],"gid":"2421329"},{"title":"Low Lights","artists":["Kanye West"],"length":131.773,"ytid":["0ZqsQ9ap5_4"],"gid":"2421965"},{"title":"Highlights","artists":["Kanye West","The-Dream","Young Thug"],"length":199.867,"ytid":["AXz78NYL4r4"],"gid":"2412664"},{"title":"Freestyle 4","artists":["Kanye West","Desiigner"],"length":123.387,"ytid":["53n94Ihfh1c"],"gid":"2421331"},{"title":"I Love Kanye","artists":["Kanye West"],"length":44.827,"ytid":["ch8g-sJb6ow"],"gid":"2422080"},{"title":"Waves","artists":["Kanye West","Chris Brown"],"length":181.573,"ytid":["Sh855LWd774"],"gid":"2412668"},{"title":"FML","artists":["Kanye West","The Weeknd"],"length":236.12,"ytid":["ZvtEQ0Vm56s"],"gid":"2421661"},{"title":"Real Friends","artists":["Kanye West","Ty Dolla \\$ign"],"length":251.573,"ytid":["AZcxZ-oiEb8"],"gid":"2403628"},{"title":"Wolves","artists":["Kanye West","Sia","VIC MENSA"],"length":301.587,"ytid":["OZHjWc0Ssvk"],"gid":"2421668"},{"title":"Frank’s Track","artists":["Kanye West","Frank Ocean"],"length":38.333,"ytid":["6oaaKNXuUv4"],"gid":"2439766"},{"title":"Siiiiiiiiilver Surffffeeeeer Intermission","artists":["Kanye West","Max B"],"length":56.56,"ytid":["SeeP7YhFy0Q"],"gid":"2421968"},{"title":"30 Hours","artists":["Kanye West"],"length":323.303,"ytid":["OH3bNgA1rkE"],"gid":"2421955"},{"title":"No More Parties in LA","artists":["Kanye West","Kendrick Lamar"],"length":374.413,"ytid":["NnMuFqsmYSE"],"gid":"2403856"},{"title":"Facts (Charlie Heat Version)","artists":["Kanye West"],"length":200.733,"ytid":["yiwDWKg9AMA"],"gid":"2399676"},{"title":"Fade","artists":["Kanye West","Post Malone","Ty Dolla \\$ign"],"length":193.748,"ytid":["JN-DCBy3hl8"],"gid":"2307999"},{"title":"Saint Pablo","artists":["Kanye West","Sampha"],"length":372.113,"ytid":["w9rzz4pDFwA"],"gid":"2428259"},{"title":"The Life Of Pablo Studio Notepad","artists":["Kanye West"],"length":0,"ytid":["MUzcrrpfYDw"],"gid":"2415045"}]