[{"title":"Trending Topic","artists":["Patrick Cc:","Beku San","Tre\\$o"],"length":159.474,"ytid":["O-Vvpod-2AY"],"gid":"6784846"},{"title":"Delightful","artists":["Patrick Cc:","Lil Uber","ZEDSU"],"length":145.655,"ytid":["Zl07sUKSeSk"],"gid":"6831446"},{"title":"Sunshine","artists":["Patrick Cc:","LAYNE","Ben Jamin (US)","Junior Dollar"],"length":213.936,"ytid":["sxiA_BX3wtQ"],"gid":"6831447"},{"title":"Falling For You","artists":["Patrick Cc:","Andre Young (CA)","Starboi Gabe"],"length":171.163,"ytid":["A9oozZFN6kY"],"gid":"6831448"},{"title":"Slip N’ Slide","artists":["Patrick Cc:","UNOWAY","Cyberlxve"],"length":177.899,"ytid":["cbQCLVFnAqg"],"gid":"6831449"},{"title":"Ashanti","artists":["Patrick Cc:","DCI","LuxxIsDead","“damn drone”"],"length":153,"ytid":["EQJpvhEDve4"],"gid":"6831450"},{"title":"Make It Out","artists":["Patrick Cc:","Lil Igloo"],"length":85.435,"ytid":["lnhB0lGLnbE"],"gid":"6831451"},{"title":"Summers End","artists":["Patrick Cc:","Yung Kage","LosingLucid","Edenmason"],"length":129.474,"ytid":["q9MhTcWEFtY"],"gid":"6831452"}]