[{"title":"Champagne Poetry","artists":["Drake"],"length":336.511,"ytid":["IxVuT8cgccM"],"gid":"6859296"},{"title":"Papi’s Home","artists":["Drake"],"length":178.623,"ytid":["RJDZBozre1g"],"gid":"7165569"},{"title":"Girls Want Girls","artists":["Drake","Lil Baby"],"length":221.98,"ytid":["b8M6N0FTpNc"],"gid":"7165581"},{"title":"In The Bible","artists":["Drake","GIVĒON","Lil Durk"],"length":296.569,"ytid":["eEdVtJW_PwE"],"gid":"7165576"},{"title":"Love All","artists":["Drake","JAY-Z"],"length":228.461,"ytid":["Pnz4wbCblmM"],"gid":"5367025"},{"title":"Fair Trade","artists":["Drake","Travis Scott"],"length":291.175,"ytid":["THVbtGqEO1o"],"gid":"6833653"},{"title":"Way 2 Sexy","artists":["Drake","Young Thug","Future"],"length":257.605,"ytid":["Qr2PWFDB4ZU"],"gid":"7139486"},{"title":"TSU","artists":["Drake"],"length":308.756,"ytid":["fhEqtynX_xc"],"gid":"5312186"},{"title":"N 2 Deep","artists":["Drake","Future"],"length":273.578,"ytid":["Oh-Al70frOc"],"gid":"7163722"},{"title":"Pipe Down","artists":["Drake"],"length":205.721,"ytid":["ZIu-V_xEehs"],"gid":"7165573"},{"title":"Yebba’s Heartbreak","artists":["Drake","Yebba"],"length":133.763,"ytid":["9rlW2rUzyn0"],"gid":"7165570"},{"title":"No Friends In The Industry","artists":["Drake"],"length":204.347,"ytid":["_dSN9EaQotw"],"gid":"7165568"},{"title":"Knife Talk","artists":["Drake","21 Savage","Project Pat"],"length":242.966,"ytid":["XqpQpt_cmhE"],"gid":"7165580"},{"title":"7AM On Bridle Path","artists":["Drake"],"length":239.635,"ytid":["L6W1_fUurpA"],"gid":"7165567"},{"title":"Race My Mind","artists":["Drake"],"length":269.884,"ytid":["bpXztWUPPFQ"],"gid":"5851754"},{"title":"Fountains","artists":["Drake","Tems"],"length":192.418,"ytid":["pwtWYFUwenE"],"gid":"7165583"},{"title":"Get Along Better","artists":["Drake","Ty Dolla \\$ign"],"length":229.304,"ytid":["84y-jaEiFZU"],"gid":"7165564"},{"title":"You Only Live Twice","artists":["Drake","Rick Ross","Lil Wayne"],"length":213.104,"ytid":["x6Nr6EX3AwY"],"gid":"7165563"},{"title":"IMY2","artists":["Drake","Kid Cudi"],"length":252.379,"ytid":["3aYA2dK2L-U"],"gid":"7165582"},{"title":"Fucking Fans","artists":["Drake"],"length":245.131,"ytid":["EK8aKKeUmmU"],"gid":"7165549"},{"title":"The Remorse","artists":["Drake"],"length":351.22,"ytid":["2_TPmfd02xc"],"gid":"7165548"}]